MANIFEST.in
README.rst
README.txt
requirements.txt
setup.py
test_requirements.txt
version.txt
cloudshell/__init__.py
cloudshell/networking/__init__.py
cloudshell/networking/networking_resource_driver_interface.py
cloudshell/networking/apply_connectivity/__init__.py
cloudshell/networking/apply_connectivity/apply_connectivity_operation.py
cloudshell/networking/apply_connectivity/models/__init__.py
cloudshell/networking/apply_connectivity/models/connectivity_request.py
cloudshell/networking/apply_connectivity/models/connectivity_result.py
cloudshell_networking.egg-info/PKG-INFO
cloudshell_networking.egg-info/SOURCES.txt
cloudshell_networking.egg-info/dependency_links.txt
cloudshell_networking.egg-info/requires.txt
cloudshell_networking.egg-info/top_level.txt
tests/__init__.py
tests/networking/__init__.py
tests/networking/test_networking_resource_driver_interface.py
tests/networking/apply_connectivity/__init__.py
tests/networking/apply_connectivity/standard_connectivity_requests.py
tests/networking/apply_connectivity/test_apply_connectivity_operation.py
tests/networking/apply_connectivity/models/__init__.py
tests/networking/apply_connectivity/models/test_connectivity_result.py