Metadata-Version: 1.0
Name: cloudshell-networking
Version: 5.1.0
Summary: QualiSystems Python package
Home-page: https://github.com/QualiSystems/cloudshell-networking
Author: QualiSystems
Author-email: info@qualisystems.com
License: UNKNOWN
Platform: UNKNOWN
